LICENSE
MANIFEST.in
README.md
README_PyPI.md
requirements.txt
setup.cfg
setup.py
data_mine/__init__.py
data_mine/__main__.py
data_mine/collection.py
data_mine/constants.py
data_mine.egg-info/PKG-INFO
data_mine.egg-info/SOURCES.txt
data_mine.egg-info/dependency_links.txt
data_mine.egg-info/not-zip-safe
data_mine.egg-info/requires.txt
data_mine.egg-info/top_level.txt
data_mine/cli/__init__.py
data_mine/cli/download_cmd.py
data_mine/nlp/__init__.py
data_mine/nlp/CSQA/__init__.py
data_mine/nlp/CSQA/constants.py
data_mine/nlp/CSQA/expected_files.txt.gz
data_mine/nlp/CSQA/loader.py
data_mine/nlp/CSQA/types.py
data_mine/nlp/CSQA/utils.py
data_mine/nlp/RACE/__init__.py
data_mine/nlp/RACE/constants.py
data_mine/nlp/RACE/expected_files.txt.gz
data_mine/nlp/RACE/loader.py
data_mine/nlp/RACE/types.py
data_mine/nlp/RACE/utils.py
data_mine/nlp/allen_ai_arc/__init__.py
data_mine/nlp/allen_ai_arc/constants.py
data_mine/nlp/allen_ai_arc/expected_files.txt.gz
data_mine/nlp/allen_ai_arc/loader.py
data_mine/nlp/allen_ai_arc/types.py
data_mine/nlp/allen_ai_arc/utils.py
data_mine/nlp/allen_ai_drop/__init__.py
data_mine/nlp/allen_ai_drop/constants.py
data_mine/nlp/allen_ai_drop/expected_files.txt.gz
data_mine/nlp/allen_ai_drop/loader.py
data_mine/nlp/allen_ai_drop/translators.py
data_mine/nlp/allen_ai_drop/types.py
data_mine/nlp/allen_ai_drop/utils.py
data_mine/nlp/allen_ai_obqa/__init__.py
data_mine/nlp/allen_ai_obqa/constants.py
data_mine/nlp/allen_ai_obqa/expected_files.txt.gz
data_mine/nlp/allen_ai_obqa/loader.py
data_mine/nlp/allen_ai_obqa/types.py
data_mine/nlp/allen_ai_obqa/utils.py
data_mine/nlp/cosmos_qa/__init__.py
data_mine/nlp/cosmos_qa/constants.py
data_mine/nlp/cosmos_qa/expected_files.txt.gz
data_mine/nlp/cosmos_qa/loader.py
data_mine/nlp/cosmos_qa/types.py
data_mine/nlp/cosmos_qa/utils.py
data_mine/nlp/hotpot_qa/__init__.py
data_mine/nlp/hotpot_qa/constants.py
data_mine/nlp/hotpot_qa/expected_files.txt.gz
data_mine/nlp/hotpot_qa/loader.py
data_mine/nlp/hotpot_qa/types.py
data_mine/nlp/hotpot_qa/utils.py
data_mine/utils/__init__.py
data_mine/utils/archive_utils.py
data_mine/utils/misc_utils.py
data_mine/utils/msg.py
data_mine/utils/requests_utils.py
